color_space_converter/__init__.py
color_space_converter/converter_baseclass.py
color_space_converter/gry_converter.py
color_space_converter/hsv_converter.py
color_space_converter/lab_converter.py
color_space_converter/lms_converter.py
color_space_converter/top_level.py
color_space_converter/xyz_converter.py
color_space_converter/yuv_converter.py
color_space_converter/bin/cli.py
color_space_converter-0.1.4.data/scripts/cli.py
test/__init__.py
test/unit_test.py
color_space_converter-0.1.4.dist-info/LICENSE
color_space_converter-0.1.4.dist-info/METADATA
color_space_converter-0.1.4.dist-info/WHEEL
color_space_converter-0.1.4.dist-info/entry_points.txt
color_space_converter-0.1.4.dist-info/top_level.txt
color_space_converter-0.1.4.dist-info/RECORD
