Metadata-Version: 2.1
Name: color-space-converter
Version: 0.1.4
Summary: Package enabling color space conversion
Home-page: http://github.com/hahnec/color-space-converter
Author: Christopher Hahne
Author-email: inbox@christopherhahne.de
License: GNU GPL V3.0
Keywords: color space model converter conversion rgb hsv yuv xyz lab lms cnn pytorch tensorflow
Platform: UNKNOWN
Requires-Python: >=3
Requires-Dist: numpy
Requires-Dist: imageio
Requires-Dist: docutils
Requires-Dist: ddt
